opvia_scripts/__init__.py
opvia_scripts/constants.py
opvia_scripts/exceptions.py
opvia_scripts/firebase.py
opvia_scripts/script_utils.py
opvia_scripts/testing.py
opvia_scripts/types/__init__.py
opvia_scripts/types/entity.py
opvia_scripts/types/result.py
opvia_scripts/types/script.py
opvia_scripts-1.5.3.dist-info/WHEEL
opvia_scripts-1.5.3.dist-info/METADATA
opvia_scripts-1.5.3.dist-info/RECORD
