Metadata-Version: 2.1
Name: opvia-scripts
Version: 1.5.3
Summary: 
Home-page: https://github.com/opvia/opvia-scripts
Requires-Python: >=3.8,<4.0
Classifier: Development Status :: 1 - Planning
Classifier: Intended Audience :: Developers
Classifier: License :: Other/Proprietary License
Classifier: Operating System :: OS Independent
Classifier: Programming Language :: Python :: 3
Classifier: Programming Language :: Python :: 3.8
Classifier: Programming Language :: Python :: 3.9
Classifier: Programming Language :: Python :: 3.10
Classifier: Programming Language :: Python :: 3.11
Classifier: Programming Language :: Python :: 3
Classifier: Programming Language :: Python :: 3 :: Only
Classifier: Programming Language :: Python :: 3.8
Classifier: Programming Language :: Python :: 3.9
Provides-Extra: docs
Requires-Dist: Pyrebase4 (>=4.5.0,<5.0.0)
Requires-Dist: altair (>=4.2.0,<5.0.0)
Requires-Dist: fastapi-camelcase (>=1.0.2,<2.0.0)
Requires-Dist: pandas (>=1.3.2,<1.5)
Requires-Dist: pydantic (>=1.8.2,<2.0.0)
Requires-Dist: requests (>=2.27.0,<3.0.0)
Requires-Dist: setuptools (==61.2.0)
Project-URL: Repository, https://github.com/opvia/opvia-scripts
